Flighter/Flighter.py
Flighter/__init__.py
Flighter/airports.py
Flighter/setup.py
Flighter-2.0.4.dist-info/METADATA
Flighter-2.0.4.dist-info/WHEEL
Flighter-2.0.4.dist-info/top_level.txt
Flighter-2.0.4.dist-info/RECORD
