Metadata-Version: 2.1
Name: Flighter
Version: 2.0.4
Summary: Flighter is an easy-to-use Python module that allows users to explore aviation using Python
Home-page: https://github.com/CoolJames1610/Flighter
Author: CoolJames1610
Author-email: jadokofie@gmail.com
License: UNKNOWN
Keywords: Flighter,Aviation,Planes,F18,RFS,ZELIKTRIC,MSFS,MFS
Platform: UNKNOWN
Classifier: Programming Language :: Python :: 3
Classifier: License :: OSI Approved :: MIT License
Classifier: Operating System :: OS Independent
Requires-Python: >=3.6
Requires-Dist: haversine
